Workbook

Sheet Summary
A1: Extraction review
A2: Source: extractions.json
A3: 74 document records
A5: Documents by type
A6: sow | B6: 18
A7: sow_amendment | B7: 6
A8: invoice | B8: 36
A9: remittance | B9: 8
A10: statement | B10: 2
A11: out_of_scope | B11: 4
A12: Total documents | B12: =SUM(B6:B11)
A14: Figures
A15: Total invoiced | B15: ='Invoices'!L39 | C15: the Invoices tab's own total, which is a SUM over its rows -- click through
A16: Invoices extracted | B16: =COUNTA('Invoices'!A2:A237) | C16: rows on the Invoices tab
A17: Invoices missing a total | B17: =COUNTBLANK('Invoices'!L2:L37) | C17: a blank total is an unreadable figure, not a zero
A18: Engagements under contract | B18: =COUNTA('Engagements'!A2:A19) | C18: one per SOW, with any amendment applied in the Current ceiling column
A19: Fields flagged for review | B19: =COUNTA('QA'!C2:C9) | C19: every low and unreadable field, listed on the QA tab with its evidence
A20: of which unreadable | B20: =COUNTIF('QA'!D2:D9,"unreadable") | C20: the figure was not on the page. Never guessed
A21: of which low confidence | B21: =COUNTIF('QA'!D2:D9,"low") | C21: read, but the reading depends on an inference that is written down
A22: Exceptions to resolve | B22: =COUNTA('Exceptions'!A2:A18) | C22: duplicates, supersessions, out-of-scope documents and unreadable figures
A23: Reviewed | B23: =COUNTA('QA'!I2:I9) | C23: fills in as somebody works down the Verdict column on the QA tab
A25: Every figure under Figures is a formula.
A26: Click one and follow it through to the rows it came from. Nothing there was computed and typed in.
A27: The counts under Documents by type are a census of the extraction itself, so they are values.
A28: Amber means low confidence, red means unreadable. Hover any filled cell for the reason.

Sheet Invoices
A1: Invoice | B1: Client | C1: Engagement | D1: PO | E1: Period | F1: Issued | G1: Due | H1: Subtotal | I1: Retainer credit | J1: Net | K1: VAT | L1: Total due | M1: Terms | N1: Source file | O1: Pages
A2: INV-2026-0876 | B2: Oakhaven Logistics Collective | C2: SOW-2026-002 | D2: PO-80678 | E2: 2026-06 | F2: 2026-07-09 | G2: 2026-08-08 | H2: 79912.83 | I2: -9814.23 | J2: 70098.6 | K2: 14019.72 | L2: 84118.32 | M2: Net 30 days from date of issue | N2: INV-2026-0876.pdf | O2: 1
A3: INV-2026-0906 | B3: Ashcombe Health Partners | C3: SOW-2026-003 | D3: PO-57052 | E3: 2026-05 | F3: 2026-06-04 | G3: 2026-07-04 | H3: 17337.79 | I3: -1293.79 | J3: 16044 | K3: 3208.8 | L3: 19252.8 | M3: Net 30 days from date of issue | N3: INV-2026-0906.pdf | O3: 1
A4: INV-2026-0912 | B4: Ashcombe Health Partners | C4: SOW-2026-003 | D4: PO-63883 | E4: 2026-06 | F4: 2026-07-07 | G4: 2026-08-06 | H4: 28951.42 | I4: -4214.42 | J4: 24737 | K4: 4947.4 | L4: 29684.4 | M4: Net 30 days from date of issue | N4: scan_20260814_114082.pdf | O4: 1
A5: INV-2026-0918 | B5: Ashcombe Health Partners | C5: SOW-2026-003 | D5: PO-93507 | E5: 2026-07 | F5: 2026-08-08 | G5: 2026-09-07 | H5: 14360.33 | I5: -717.83 | J5: 13642.5 | K5: 2728.5 | L5: 16371 | M5: Net 30 days from date of issue | N5: scan_20260814_114765.pdf | O5: 1
A6: INV-2026-0966 | B6: Pentland Media Group | C6: SOW-2026-005 | D6: PO-58393 | E6: 2026-07 | F6: 2026-07-25 | G6: 2026-08-24 | H6: 33546.78 | I6: -5830.44 | J6: 27716.34 | K6: 5543.27 | L6: 33259.61 | M6: Net 30 days from date of issue | N6: INV-2026-0966.pdf | O6: 1
A7: INV-2026-1032 | B7: Braemar Retail Corporation | C7: SOW-2026-007 | D7: PO-19116 | E7: 2026-05 | F7: 2026-06-07 | G7: 2026-07-07 | H7: 29279.55 | I7: -4053.55 | J7: 25226 | K7: 5045.2 | L7: 30271.2 | M7: Net 30 days from date of issue | N7: scan_20260814_115456.pdf | O7: 1
A8: INV-2026-1038 | B8: Braemar Retail Corporation | C8: SOW-2026-007 | D8: PO-65296 | E8: 2026-06 | F8: 2026-07-03 | G8: 2026-08-02 | H8: 32064.86 | I8: -4422.78 | J8: 27642.08 | K8: 5528.42 | L8: 33170.5 | M8: Net 30 days from date of issue | N8: INV-2026-1038.pdf | O8: 1
A9: INV-2026-1044 | B9: Braemar Retail Corporation | C9: SOW-2026-007 | D9: PO-63264 | E9: 2026-07 | F9: 2026-08-07 | G9: 2026-09-06 | H9: 37653.79 | I9: -4332.29 | J9: 33321.5 | K9: 6664.3 | L9: 39985.8 | M9: Net 30 days from date of issue | N9: scan_20260814_115806.pdf | O9: 1
A10: INV-2026-1050 | B10: Braemar Retail Corporation | C10: SOW-2025-008 | D10: PO-31319 | E10: 2026-05 | F10: 2026-05-23 | G10: 2026-06-22 | H10: 37279.1 | I10: -2128.33 | J10: 35150.77 | K10: 7030.15 | L10: 42180.92 | M10: Net 30 days from date of issue | N10: scan_20260814_116655.pdf | O10: 1
A11: INV-2026-1062 | B11: Northfield Municipal Group | C11: SOW-2026-009 | D11: PO-70589 | E11: 2026-05 | F11: 2026-05-29 | G11: 2026-06-28 | H11: 22075.11 | I11: -4557.89 | J11: 17517.22 | K11: 3503.44 | L11: 21020.66 | M11: Net 30 days from date of issue | N11: INV-2026-1062.pdf | O11: 1
A12: INV-2026-1068 | B12: Northfield Municipal Group | C12: SOW-2026-009 | D12: PO-71694 | E12: 2026-07 | F12: 2026-07-26 | G12: 2026-08-25 | H12: 45530.86 | I12: -1737.82 | J12: 43793.04 | K12: 8758.61 | L12: 52551.65 | M12: Net 30 days from date of issue | N12: INV-2026-1068.pdf | O12: 1
A13: INV-2026-1146 | B13: Stonebridge Energy Group | C13: SOW-2026-012 | D13: PO-37653 | E13: 2026-05 | F13: 2026-06-05 | G13: 2026-07-05 | H13: 31696.19 | I13: -1512.44 | J13: 30183.75 | K13: 6036.75 | L13: 36220.5 | M13: Net 30 days from date of issue | N13: INV-2026-1146.pdf | O13: 1
... A26: INV-2026-1494 | B26: Thornbury Retail Partners | C26: SOW-2025-019 | D26: PO-36071 | E26: 2026-05 | F26: 2026-06-04 | G26: 2026-07-04 | H26: 14795.01 | I26: -3137.34 | J26: 11657.67 | K26: 2331.53 | L26: 13989.2 | M26: Net 30 days from date of issue | N26: INV-2026-1494.pdf | O26: 1
A27: INV-2026-1500 | B27: Thornbury Retail Partners | C27: SOW-2025-019 | D27: PO-96163 | E27: 2026-06 | F27: 2026-07-05 | G27: 2026-08-04 | N27: scan_20260814_119189.pdf | O27: 1
A28: INV-2026-1506 | B28: Thornbury Retail Partners | C28: SOW-2025-019 | D28: PO-48752 | E28: 2026-07 | F28: 2026-08-08 | G28: 2026-09-07 | H28: 17865.34 | I28: -1168.51 | J28: 16696.83 | K28: 3339.37 | L28: 20036.2 | M28: Net 30 days from date of issue | N28: scan_20260814_119479.pdf | O28: 1
A29: INV-2026-1512 | B29: Quarrymoor Transit Partners | C29: SOW-2025-020 | D29: PO-41385 | E29: 2026-05 | F29: 2026-05-22 | G29: 2026-06-21 | H29: 364020.5 | I29: -68060.71 | J29: 295959.79 | K29: 59191.96 | L29: 355151.75 | M29: Net 30 days from date of issue | N29: scan_20260814_119811.pdf | O29: 1
A30: INV-2026-1596 | B30: Fernhollow Financial Trust | C30: SOW-2026-022 | D30: PO-82063 | E30: 2026-05 | F30: 2026-06-05 | G30: 2026-07-05 | H30: 34439.75 | I30: -1961.08 | J30: 32478.67 | K30: 6495.73 | L30: 38974.4 | M30: Net 30 days from date of issue | N30: scan_20260814_120638.pdf | O30: 1
A31: INV-2026-1602 | B31: Fernhollow Financial Trust | C31: SOW-2026-022 | D31: PO-11220 | E31: 2026-06 | F31: 2026-07-05 | G31: 2026-08-04 | H31: 38860.26 | I31: -3850.43 | J31: 35009.83 | K31: 7001.97 | L31: 42011.8 | M31: Net 30 days from date of issue | N31: INV-2026-1602.pdf | O31: 1
A32: INV-2026-1608 | B32: Fernhollow Financial Trust | C32: SOW-2026-022 | D32: PO-47606 | E32: 2026-07 | F32: 2026-08-06 | G32: 2026-09-05 | H32: 46668.24 | I32: -9351.99 | J32: 37316.25 | K32: 7463.25 | L32: 44779.5 | M32: Net 30 days from date of issue | N32: INV-2026-1608.pdf | O32: 1
A33: INV-2026-1614 | B33: Fernhollow Financial Trust | C33: SOW-2025-023 | D33: PO-77839 | E33: 2026-05 | F33: 2026-05-10 | G33: 2026-06-09 | H33: 196942.78 | I33: -34181.64 | J33: 162761.14 | K33: 32552.23 | L33: 195313.37 | M33: Net 30 days from date of issue | N33: INV-2026-1614.pdf | O33: 1
A34: INV-2026-1704 | B34: Stonebridge Energy Group | C34: SOW-2025-025 | D34: PO-92719 | E34: 2026-05 | F34: 2026-06-06 | G34: 2026-07-06 | H34: 50409.48 | I34: -6214.06 | J34: 44195.42 | K34: 8839.08 | L34: 53034.5 | M34: Net 30 days from date of issue | N34: INV-2026-1704.pdf | O34: 1
A35: INV-2026-1710 | B35: Stonebridge Energy Group | C35: SOW-2025-025 | D35: PO-67433 | E35: 2026-06 | F35: 2026-07-06 | G35: 2026-08-05 | H35: 44554.05 | I35: -7397.72 | J35: 37156.33 | K35: 7431.27 | L35: 44587.6 | M35: Net 30 days from date of issue | N35: scan_20260814_121161.pdf | O35: 1
A36: INV-2026-1716 | B36: Stonebridge Energy Group | C36: SOW-2025-025 | D36: PO-96356 | E36: 2026-07 | F36: 2026-08-06 | G36: 2026-09-05 | H36: 38108.89 | I36: -5800.56 | J36: 32308.33 | K36: 6461.67 | L36: 38770 | M36: Net 30 days from date of issue | N36: scan_20260814_121516.pdf | O36: 1
A37: INV-2026-1836 | B37: Merrivale Maritime Corporation | C37: SOW-2026-029 | D37: PO-36685 | E37: 2026-06 | F37: 2026-06-14 | G37: 2026-07-14 | H37: 57932.19 | I37: -4276.1 | J37: 53656.09 | K37: 10731.22 | L37: 64387.31 | M37: Net 30 days from date of issue | N37: scan_20260814_121921.pdf | O37: 1
K39: TOTAL INVOICED | L39: =SUM(L2:L37)

Sheet Engagements
A1: SOW | B1: Client | C1: Engagement | D1: Fee basis | E1: Start | F1: End | G1: Ceiling hours | H1: Ceiling amount | I1: Amended by | J1: Revised ceiling | K1: Revised end | L1: Current ceiling | M1: Source file | N1: Pages
A2: SOW-2025-008 | B2: Braemar Retail Corporation | C2: Regulatory Reporting Programme | D2: Fixed fee | E2: 2025-11-16 | F2: 2027-05-12 | G2: 1020 | H2: 274176 | L2: =H2 | M2: Braemar Retail Corporation - SOW - SOW-2025-008 FINAL v3 (signed).docx | N2: 1
A3: SOW-2025-011 | B3: Lowmarsh Retail Partners | C3: Inventory Modernisation | D3: Fixed fee | E3: 2025-10-11 | F3: 2027-05-02 | G3: 4940 | H3: 1332713.2 | I3: SOW-2025-011-A3 | J3: 1665891.5 | K3: 2027-06-30 | L3: =IF(J3="",H3,J3) | M3: Lowmarsh Retail Partners - SOW - SOW-2025-011 FINAL v3 (signed).docx | N3: 1
A4: SOW-2025-013 | B4: Ashcombe Health Partners | C4: Payments Assessment | D4: Time and materials | E4: 2025-09-28 | F4: 2026-12-08 | G4: 3200 | H4: 812800 | L4: =H4 | M4: Ashcombe Health Partners - SOW - SOW-2025-013 FINAL v3 (signed).docx | N4: 1
A5: SOW-2025-015 | B5: Ashcombe Health Partners | C5: Workforce Planning Programme | D5: Time and materials | E5: 2025-11-04 | F5: 2026-10-16 | G5: 3540 | H5: 1069080 | I5: SOW-2025-015-A4 | J5: 1208060.4 | K5: 2027-01-25 | L5: =IF(J5="",H5,J5) | M5: Ashcombe Health Partners - SOW - SOW-2025-015 FINAL v3 (signed).docx | N5: 1
A6: SOW-2025-016 | B6: Braemar Retail Corporation | C6: Field Operations Rollout | D6: Time and materials | E6: 2025-09-01 | F6: 2027-03-09 | G6: 7980 | H6: 1955100 | L6: =H6 | M6: Braemar Retail Corporation - SOW - SOW-2025-016 FINAL v3 (signed).docx | N6: 1
A7: SOW-2025-018 | B7: Thornbury Retail Partners | C7: Payments Modernisation | D7: Fixed fee | E7: 2025-12-04 | F7: 2026-12-04 | G7: 820 | H7: 217906.8 | L7: =H7 | M7: Thornbury Retail Partners - SOW - SOW-2025-018 FINAL v3 (signed).docx | N7: 1
A8: SOW-2025-019 | B8: Thornbury Retail Partners | C8: Grid Analytics Assessment | D8: Time and materials | E8: 2025-12-03 | F8: 2026-10-10 | G8: 940 | H8: 262260 | I8: SOW-2025-019-A5 | J8: 361918.8 | K8: 2026-12-07 | L8: =IF(J8="",H8,J8) | M8: Thornbury Retail Partners - SOW - SOW-2025-019 FINAL v3 (signed).docx | N8: 1
A9: SOW-2025-020 | B9: Quarrymoor Transit Partners | C9: Inventory Implementation | D9: Fixed fee | E9: 2025-11-30 | F9: 2027-04-16 | G9: 4840 | H9: 1154243.2 | L9: =H9 | M9: Quarrymoor Transit Partners - SOW - SOW-2025-020 FINAL v3 (signed).docx | N9: 1
A10: SOW-2025-023 | B10: Fernhollow Financial Trust | C10: Asset Register Assessment | D10: Fixed fee | E10: 2025-12-30 | F10: 2027-01-11 | G10: 1840 | H10: 455731.2 | I10: SOW-2025-023-A6 | J10: 587893.25 | K10: 2027-02-10 | L10: =IF(J10="",H10,J10) | M10: Fernhollow Financial Trust - SOW - SOW-2025-023 FINAL v3 (signed).docx | N10: 1
A11: SOW-2025-025 | B11: Stonebridge Energy Group | C11: Billing Platform Implementation | D11: Time and materials | E11: 2025-11-11 | F11: 2026-10-25 | G11: 2440 | H11: 688080 | L11: =H11 | M11: Stonebridge Energy Group - SOW - SOW-2025-025 FINAL v3 (signed).docx | N11: 1
A12: SOW-2026-002 | B12: Oakhaven Logistics Collective | C12: Credit Risk Migration | D12: Fixed fee | E12: 2026-01-28 | F12: 2026-08-21 | G12: 1980 | H12: 420591.6 | I12: SOW-2026-002-A1 | J12: 492092.17 | K12: 2026-12-04 | L12: =IF(J12="",H12,J12) | M12: Oakhaven Logistics Collective - SOW - SOW-2026-002 FINAL v3 (signed).docx | N12: 1
A13: SOW-2026-003 | B13: Ashcombe Health Partners | C13: Revenue Assurance Optimisation | D13: Time and materials | E13: 2026-01-09 | F13: 2026-10-31 | G13: 940 | H13: 232180 | L13: =H13 | M13: Ashcombe Health Partners - SOW - SOW-2026-003 FINAL v3 (signed).docx | N13: 1
A14: SOW-2026-005 | B14: Pentland Media Group | C14: Procurement Modernisation | D14: Fixed fee | E14: 2026-01-31 | F14: 2026-10-10 | G14: 2690 | H14: 133038.43 | L14: =H14 | M14: Pentland Media Group - SOW - SOW-2026-005 FINAL v3 (signed).docx | N14: 1
A15: SOW-2026-007 | B15: Braemar Retail Corporation | C15: Revenue Assurance Discovery | D15: Time and materials | E15: 2026-02-19 | F15: 2027-02-27 | G15: 1480 | H15: 393680 | I15: SOW-2026-007-A2 | J15: 448795.2 | K15: 2027-04-01 | L15: =IF(J15="",H15,J15) | M15: Braemar Retail Corporation - SOW - SOW-2026-007 FINAL v3 (signed).docx | N15: 1
A16: SOW-2026-009 | B16: Northfield Municipal Group | C16: Pricing Modernisation | D16: Fixed fee | E16: 2026-01-23 | F16: 2026-11-10 | G16: 780 | H16: 241737.6 | L16: =H16 | M16: Northfield Municipal Group - SOW - SOW-2026-009 FINAL v3 (signed).docx | N16: 1
A17: SOW-2026-012 | B17: Stonebridge Energy Group | C17: Credit Risk Programme | D17: Time and materials | E17: 2026-01-14 | F17: 2026-09-24 | G17: 1480 | H17: 478040 | L17: =H17 | M17: Stonebridge Energy Group - SOW - SOW-2026-012 FINAL v3 (signed).docx | N17: 1
A18: SOW-2026-022 | B18: Fernhollow Financial Trust | C18: Billing Platform Assessment | D18: Time and materials | E18: 2026-02-19 | F18: 2027-01-25 | G18: 1520 | H18: 443840 | L18: =H18 | M18: Fernhollow Financial Trust - SOW - SOW-2026-022 FINAL v3 (signed).docx | N18: 1
A19: SOW-2026-029 | B19: Merrivale Maritime Corporation | C19: Grid Analytics Integration | D19: Fixed fee | E19: 2026-01-26 | F19: 2026-12-26 | G19: 1960 | H19: 482904.8 | L19: =H19 | M19: Merrivale Maritime Corporation - SOW - SOW-2026-029 FINAL v3 (signed).docx | N19: 1

Sheet Exceptions
A1: Document | B1: Type | C1: Issue | D1: Detail | E1: Source file
A2: FW_ Your Meridian Print account.eml | B2: out_of_scope | C2: out of scope | D2: not the firm's paperwork; no fields extracted | E2: FW_ Your Meridian Print account.eml
A3: INV-2026-1500 | B3: invoice | C3: total_due unreadable | D3: the scan ends immediately after the third line item; the whole totals block, including the TOTAL DUE line, is below the scan margin and is not on the page. REM-2026-8461 in this same folder settles INV-2026-1500 at 34,906.40, but that figure belongs to the remittance and has deliberately not been carried across to this invoice | E3: scan_20260814_119189.pdf
A4: INV-2026-1596 | B4: invoice | C4: payment_terms contradicted | D4: a handwritten note below the payment block reads 'net 14 days not 30 -- agreed w/ MJ 12/8', contradicting the printed terms. The printed value is recorded; the annotation is unsigned and undated as to year and has not been applied | E4: scan_20260814_120638.pdf
A5: INV-2026-1614 | B5: invoice | C5: duplicate | D5: a second copy of INV-2026-1614; excluded from totals | E5: INV-2026-1614 (1).pdf
A6: SOW-2025-011-A3 | B6: sow_amendment | C6: supersedes | D6: replaces SOW-2025-011, whose figures are stale | E6: Lowmarsh Retail Partners - SOW-2025-011 amendment A3.docx
A7: SOW-2025-015-A4 | B7: sow_amendment | C7: supersedes | D7: replaces SOW-2025-015, whose figures are stale | E7: Ashcombe Health Partners - SOW-2025-015 amendment A4.docx
A8: SOW-2025-019-A5 | B8: sow_amendment | C8: supersedes | D8: replaces SOW-2025-019, whose figures are stale | E8: Thornbury Retail Partners - SOW-2025-019 amendment A5.docx
A9: SOW-2025-023-A6 | B9: sow_amendment | C9: supersedes | D9: replaces SOW-2025-023, whose figures are stale | E9: Fernhollow Financial Trust - SOW-2025-023 amendment A6.docx
A10: SOW-2026-002-A1 | B10: sow_amendment | C10: supersedes | D10: replaces SOW-2026-002, whose figures are stale | E10: Oakhaven Logistics Collective - SOW-2026-002 amendment A1.docx
A11: SOW-2026-007-A2 | B11: sow_amendment | C11: supersedes | D11: replaces SOW-2026-007, whose figures are stale | E11: Braemar Retail Corporation - SOW-2026-007 amendment A2.docx
A12: STM-2026-101 | B12: statement | C12: invoice_count unreadable | D12: the INVOICES OUTSTANDING label is present but cell E18 holds the uncalculated formula =COUNT(E13:E15) with no stored result, so the workbook states no count | E12: Statement of account - Ashcombe Health Partners - Aug 2026.xlsx
... A18: scan_20260814_124109.pdf | B18: out_of_scope | C18: out of scope | D18: not the firm's paperwork; no fields extracted | E18: scan_20260814_124109.pdf

Sheet QA
A1: Document | B1: Type | C1: Field | D1: Confidence | E1: Value | F1: Evidence | G1: Reason | H1: Source file | I1: Verdict
A2: INV-2026-1212 | B2: invoice | C2: due_date | D2: low | E2: 2026-07-03 | F2: page 1, header block, right column, 'Payment due' row | G2: printed 03/07/2026, ambiguous between day-first and month-first; read day-first to match the issue date on the same document and the printed Net 30 day terms | H2: INV-2026-1212.pdf
A3: INV-2026-1212 | B3: invoice | C3: issue_date | D3: low | E3: 2026-06-03 | F3: page 1, header block, right column, 'Issue date' row | G3: printed 03/06/2026, which is ambiguous between day-first and month-first; read day-first because the billing period printed on the same document is May 2026 and the SOW invoices monthly in arrears, and because the printed payment due date 03/07/2026 is exactly the stated Net 30 days later only on the day-first reading | H3: INV-2026-1212.pdf
A4: INV-2026-1500 | B4: invoice | C4: total_due | D4: unreadable | G4: the scan ends immediately after the third line item; the whole totals block, including the TOTAL DUE line, is below the scan margin and is not on the page. REM-2026-8461 in this same folder settles INV-2026-1500 at 34,906.40, but that figure belongs to the remittance and has deliberately not been carried across to this invoice | H4: scan_20260814_119189.pdf
A5: INV-2026-1596 | B5: invoice | C5: payment_terms | D5: low | E5: Net 30 days from date of issue | F5: page 1, payment terms line beneath the totals block | G5: a handwritten note below the payment block reads 'net 14 days not 30 -- agreed w/ MJ 12/8', contradicting the printed terms. The printed value is recorded; the annotation is unsigned and undated as to year and has not been applied | H5: scan_20260814_120638.pdf
A6: STM-2026-101 | B6: statement | C6: invoice_count | D6: unreadable | G6: the INVOICES OUTSTANDING label is present but cell E18 holds the uncalculated formula =COUNT(E13:E15) with no stored result, so the workbook states no count | H6: Statement of account - Ashcombe Health Partners - Aug 2026.xlsx
A7: STM-2026-101 | B7: statement | C7: total_outstanding | D7: unreadable | G7: the TOTAL OUTSTANDING label is present but cell E17 holds the uncalculated formula =SUM(E13:E15) with no stored result, so the workbook states no balance. It could be recomputed from the amounts in rows 13 to 15, but that figure would be mine and not the statement's, so it is not recorded here | H7: Statement of account - Ashcombe Health Partners - Aug 2026.xlsx
A8: STM-2026-102 | B8: statement | C8: invoice_count | D8: unreadable | G8: the INVOICES OUTSTANDING label is present but cell E17 holds the uncalculated formula =COUNT(E13:E14) with no stored result, so the workbook states no count | H8: Statement of account - Fernhollow Financial Trust - Aug 2026.xlsx
A9: STM-2026-102 | B9: statement | C9: total_outstanding | D9: unreadable | G9: the TOTAL OUTSTANDING label is present but cell E16 holds the uncalculated formula =SUM(E13:E14) with no stored result, so the workbook states no balance. It could be recomputed from the amounts in rows 13 to 14, but that figure would be mine and not the statement's, so it is not recorded here | H9: Statement of account - Fernhollow Financial Trust - Aug 2026.xlsx
